pyasyncsql/__init__.py
pyasyncsql/core.py
asyncsqlpy-0.1.8.dist-info/METADATA
asyncsqlpy-0.1.8.dist-info/WHEEL
asyncsqlpy-0.1.8.dist-info/top_level.txt
asyncsqlpy-0.1.8.dist-info/RECORD
