Metadata-Version: 2.4
Name: asyncsqlpy
Version: 0.1.8
Summary: Async SQL + Redis wrapper with Mongo-like interface, fire-and-forget SQL background updates.
Author-email: sathish20004 <sourechebala19470@gmail.com>, Sathishzus <sathishzus@ridemap.in>
License: MIT
Project-URL: Homepage, https://github.com/sathishzuss/pyasyncsql
Keywords: async,postgresql,redis,mongodb,jsonb,aiopg,aioredis
Requires-Python: >=3.9
Requires-Dist: aiopg>=1.3.0
Requires-Dist: redis>=5.0.0
